README.md
setup.cfg
setup.py
blockchainetl/__init__.py
blockchainetl/atomic_counter.py
blockchainetl/csv_utils.py
blockchainetl/exporters.py
blockchainetl/file_utils.py
blockchainetl/logging_utils.py
blockchainetl/jobs/__init__.py
blockchainetl/jobs/base_job.py
blockchainetl/jobs/exporters/__init__.py
blockchainetl/jobs/exporters/composite_item_exporter.py
blockchainetl/jobs/exporters/console_item_exporter.py
blockchainetl/jobs/exporters/google_pubsub_item_exporter.py
blockchainetl/jobs/exporters/in_memory_item_exporter.py
blockchainetl/jobs/exporters/postgres_item_exporter.py
blockchainetl/streaming/__init__.py
blockchainetl/streaming/postgres_utils.py
blockchainetl/streaming/streamer.py
blockchainetl/streaming/streamer_adapter_stub.py
blockchainetl/streaming/streaming_utils.py
theta_etl.egg-info/PKG-INFO
theta_etl.egg-info/SOURCES.txt
theta_etl.egg-info/dependency_links.txt
theta_etl.egg-info/entry_points.txt
theta_etl.egg-info/requires.txt
theta_etl.egg-info/top_level.txt
thetaetl/__init__.py
thetaetl/__main__.py
thetaetl/atomic_counter.py
thetaetl/csv_utils.py
thetaetl/erc20_abi.py
thetaetl/exporters.py
thetaetl/json_rpc_requests.py
thetaetl/mainnet_daofork_state_changes.py
thetaetl/mainnet_genesis_alloc.py
thetaetl/misc_utils.py
thetaetl/progress_logger.py
thetaetl/thread_local_proxy.py
thetaetl/utils.py
thetaetl/cli/__init__.py
thetaetl/cli/export_all.py
thetaetl/cli/export_blocks_and_transactions.py
thetaetl/cli/export_contracts.py
thetaetl/cli/export_traces.py
thetaetl/cli/extract_contracts.py
thetaetl/cli/extract_csv_column.py
thetaetl/cli/filter_items.py
thetaetl/cli/get_block_range_for_date.py
thetaetl/cli/get_block_range_for_timestamps.py
thetaetl/cli/get_keccak_hash.py
thetaetl/cli/stream.py
thetaetl/domain/__init__.py
thetaetl/domain/block.py
thetaetl/domain/coins.py
thetaetl/domain/coins_input.py
thetaetl/domain/coins_output.py
thetaetl/domain/contract.py
thetaetl/domain/guardian_votes.py
thetaetl/domain/hcc.py
thetaetl/domain/status.py
thetaetl/domain/trace.py
thetaetl/domain/transaction.py
thetaetl/domain/vote.py
thetaetl/domain/raw_transaction/__init__.py
thetaetl/domain/raw_transaction/coinbase_tx.py
