Metadata-Version: 2.1
Name: theta-etl
Version: 0.1.11
Summary: Tools for exporting Theta blockchain data to CSV or JSON
Home-page: https://github.com/jingxu85/theta-etl
Author: Thetalabs
Author-email: jing@thetalabs.org
License: UNKNOWN
Project-URL: Source, https://github.com/jingxu85/theta-etl
Project-URL: Bug Reports, https://github.com/jingxu85/theta-etl/issues
Keywords: theta
Platform: UNKNOWN
Classifier: Development Status :: 5 - Production/Stable
Classifier: Intended Audience :: Developers
Classifier: License :: OSI Approved :: MIT License
Classifier: Programming Language :: Python :: 3
Classifier: Programming Language :: Python :: 3.5
Classifier: Programming Language :: Python :: 3.6
Classifier: Programming Language :: Python :: 3.7
Requires-Python: >=3.5.3,<3.8.0
Provides-Extra: streaming
Provides-Extra: dev
